Metadata-Version: 2.1
Name: bode_utils
Version: 1.1.1
Summary: package for generating Bode plots
Home-page: https://github.com/ryanGT/bode_utils
Author: Ryan Krauss
Author-email: ryanwkrauss@gmail.com
Classifier: Programming Language :: Python :: 3
Classifier: License :: OSI Approved :: MIT License
Classifier: Operating System :: OS Independent
License-File: LICENSE
